php_whisperer/__init__.py
php_whisperer/generate_php.py
php_whisperer/read_php.py
php_whisperer-3.0.0.dist-info/LICENSE
php_whisperer-3.0.0.dist-info/METADATA
php_whisperer-3.0.0.dist-info/WHEEL
php_whisperer-3.0.0.dist-info/entry_points.txt
php_whisperer-3.0.0.dist-info/top_level.txt
php_whisperer-3.0.0.dist-info/RECORD
