Metadata-Version: 2.1
Name: php-whisperer
Version: 3.0.0
Summary: Read and write php arrays with python
Home-page: https://github.com/matthewnicol/php_whisperer
Author: Matthew Nicol
Author-email: matthew.b.nicol@gmail.com
Classifier: Programming Language :: Python :: 3
Classifier: License :: OSI Approved :: MIT License
Classifier: Operating System :: OS Independent
License-File: LICENSE
